my_pivoting/__init__.py
my_pivoting/pivoting.py
my_pivoting-0.1.1.dist-info/WHEEL
my_pivoting-0.1.1.dist-info/METADATA
my_pivoting-0.1.1.dist-info/RECORD
