Metadata-Version: 2.1
Name: my-pivoting
Version: 0.1.1
Summary: 
Author: Egor Krapivin
Author-email: egor.krapivin98@gmail.com
Requires-Python: >=3.7,<4.0
Classifier: Programming Language :: Python :: 3
Classifier: Programming Language :: Python :: 3.10
Classifier: Programming Language :: Python :: 3.7
Classifier: Programming Language :: Python :: 3.8
Classifier: Programming Language :: Python :: 3.9
Requires-Dist: pandas (>=1.4.4,<2.0.0)
